htmlit2/block.py
htmlit2/example.py
htmlit2/example1.py
htmlit2/example_2.py
htmlit2/plotly_utils.py
htmlit2/templates/base.html
htmlit2/templates/index.html
htmlit2/templates/style.css
htmlit-0.1.9.dist-info/LICENSE
htmlit-0.1.9.dist-info/METADATA
htmlit-0.1.9.dist-info/WHEEL
htmlit-0.1.9.dist-info/top_level.txt
htmlit-0.1.9.dist-info/RECORD
