Metadata-Version: 2.1
Name: htmlit
Version: 0.1.9
Summary: Description
Home-page: https://github.com/GaetanDesrues/htmlgen
Author: Gaetan Desrues
Author-email: gdesrues@gmail.com
License: UNKNOWN
Platform: UNKNOWN
Classifier: Programming Language :: Python :: 3
Classifier: License :: OSI Approved :: MIT License
Classifier: Operating System :: OS Independent
License-File: LICENSE
